el_loom_api_client/__init__.py
el_loom_api_client/_client.py
el_loom_api_client/_config.py
el_loom_api_client/api/__init__.py
el_loom_api_client/api/error.py
el_loom_api_client/api/experiment.py
el_loom_api_client/api/request.py
el_loom_api_client/models.py
el_loom_api_client/utilities.py
el_loom_api_client-0.3.0.dist-info/WHEEL
el_loom_api_client-0.3.0.dist-info/METADATA
el_loom_api_client-0.3.0.dist-info/RECORD
