Metadata-Version: 2.4
Name: el-loom-api-client
Version: 0.3.0
License-Expression: MIT
Requires-Dist: httpx>=0.28.1
Requires-Dist: pydantic>=2.11.7
Requires-Dist: numpy
Requires-Dist: matplotlib
Requires-Dist: pydantic-settings>=2.10.1
Requires-Python: >=3.12
